lapwing/__about__.py
lapwing/__init__.py
lapwing/cmd.py
lapwing/project_template/manage.py
lapwing/project_template/home/__init__.py
lapwing/project_template/home/models.py
lapwing/project_template/home/migrations/0001_initial.py
lapwing/project_template/home/migrations/0002_create_homepage.py
lapwing/project_template/home/migrations/__init__.py
lapwing/project_template/home/static/css/welcome_page.css
lapwing/project_template/home/templates/home/home_page.html
lapwing/project_template/home/templates/home/welcome_page.html
lapwing/project_template/project_name/__init__.py
lapwing/project_template/project_name/urls.py
lapwing/project_template/project_name/wsgi.py
lapwing/project_template/project_name/settings/__init__.py
lapwing/project_template/project_name/settings/django.py
lapwing/project_template/project_name/settings/wagtail.py
lapwing/project_template/project_name/templates/404.html
lapwing/project_template/project_name/templates/500.html
lapwing/project_template/project_name/templates/base.html
lapwing/project_template/search/__init__.py
lapwing/project_template/search/views.py
lapwing/project_template/search/templates/search/search.html
lapwing-0.1.dist-info/METADATA
lapwing-0.1.dist-info/WHEEL
lapwing-0.1.dist-info/entry_points.txt
lapwing-0.1.dist-info/licenses/LICENSE.txt
lapwing-0.1.dist-info/RECORD
